pyrpl/__init__.py
pyrpl/__main__.py
pyrpl/_version.py
pyrpl/acquisition_module.py
pyrpl/async_utils.py
pyrpl/attributes.py
pyrpl/curvedb.py
pyrpl/errors.py
pyrpl/memory.py
pyrpl/module_attributes.py
pyrpl/modules.py
pyrpl/pyrpl.py
pyrpl/pyrpl_utils.py
pyrpl/redpitaya.py
pyrpl/redpitaya_client.py
pyrpl/sshshell.py
pyrpl/config/global_config.yml
pyrpl/config/nosetests_source.yml
pyrpl/config/nosetests_source_dummy_module.yml
pyrpl/config/nosetests_source_lockbox.yml
pyrpl/fpga/Makefile
pyrpl/fpga/README.md
pyrpl/fpga/make.bat
pyrpl/fpga/red_pitaya.bin
pyrpl/fpga/red_pitaya_vivado.tcl
pyrpl/fpga/red_pitaya_withPRNG.bin
pyrpl/fpga/settings.sh
pyrpl/hardware_modules/__init__.py
pyrpl/hardware_modules/ams.py
pyrpl/hardware_modules/asg.py
pyrpl/hardware_modules/dsp.py
pyrpl/hardware_modules/filter.py
pyrpl/hardware_modules/hk.py
pyrpl/hardware_modules/iq.py
pyrpl/hardware_modules/pid.py
pyrpl/hardware_modules/pwm.py
pyrpl/hardware_modules/sampler.py
pyrpl/hardware_modules/scope.py
pyrpl/hardware_modules/trig.py
pyrpl/hardware_modules/iir/__init__.py
pyrpl/hardware_modules/iir/iir.py
pyrpl/hardware_modules/iir/iir_theory.py
pyrpl/monitor_server/Makefile
pyrpl/monitor_server/monitor_server
pyrpl/monitor_server/monitor_server.c
pyrpl/monitor_server/monitor_server_0.95
pyrpl/software_modules/__init__.py
pyrpl/software_modules/curve_viewer.py
pyrpl/software_modules/loop.py
pyrpl/software_modules/module_managers.py
pyrpl/software_modules/network_analyzer.py
pyrpl/software_modules/pyrpl_config.py
pyrpl/software_modules/software_pid.py
pyrpl/software_modules/spectrum_analyzer.py
pyrpl/software_modules/lockbox/__init__.py
pyrpl/software_modules/lockbox/gainoptimizer.py
pyrpl/software_modules/lockbox/input.py
pyrpl/software_modules/lockbox/lockbox.py
pyrpl/software_modules/lockbox/output.py
pyrpl/software_modules/lockbox/stage.py
pyrpl/software_modules/lockbox/models/__init__.py
pyrpl-0.9.3.6.dist-info/DESCRIPTION.rst
pyrpl-0.9.3.6.dist-info/METADATA
pyrpl-0.9.3.6.dist-info/RECORD
pyrpl-0.9.3.6.dist-info/WHEEL
pyrpl-0.9.3.6.dist-info/metadata.json
pyrpl-0.9.3.6.dist-info/top_level.txt
