Metadata-Version: 2.0
Name: pyrpl
Version: 0.9.3.6
Summary: DSP servo controller for quantum optics with the RedPitaya
Home-page: http://lneuhaus.github.io/pyrpl/
Author: Leonhard Neuhaus
Author-email: neuhaus@lkb.upmc.fr
License: GPLv3
Keywords: RedPitaya DSP FPGA IIR PDH synchronous detection filter PID control lockbox servo feedback lock quantum optics
Platform: any
Classifier: Programming Language :: Python :: 2.7
Classifier: Programming Language :: Python :: 3.4
Classifier: Programming Language :: Python :: 3.5
Classifier: Programming Language :: Python :: 3.6
Classifier: Programming Language :: C
Classifier: Natural Language :: English
Classifier: Development Status :: 4 - Beta
Classifier: License :: OSI Approved :: GNU General Public License v3 (GPLv3)
Classifier: Topic :: Scientific/Engineering :: Human Machine Interfaces
Classifier: Topic :: Scientific/Engineering :: Physics
Requires-Dist: futures
Requires-Dist: nose (>=1.0)
Requires-Dist: numpy (>=1.9)
Requires-Dist: pandas
Requires-Dist: paramiko (>=2.0)
Requires-Dist: pyqtgraph
Requires-Dist: pyyaml
Requires-Dist: qtpy
Requires-Dist: scipy
Requires-Dist: scp
